perigon/__init__.py
perigon/api/__init__.py
perigon/api/supplemental_endpoints_api.py
perigon/api/v1_api.py
perigon/api_client.py
perigon/api_response.py
perigon/exceptions.py
perigon/models/__init__.py
perigon/models/all_endpoint_sort_by.py
perigon/models/article.py
perigon/models/article_search_filter.py
perigon/models/article_search_params.py
perigon/models/articles_vector_search_result.py
perigon/models/auth_exception.py
perigon/models/auth_exception_cause.py
perigon/models/auth_exception_cause_stack_trace_inner.py
perigon/models/auth_exception_suppressed_inner.py
perigon/models/category_holder.py
perigon/models/category_with_score_holder.py
perigon/models/company.py
perigon/models/company_count.py
perigon/models/company_holder.py
perigon/models/company_search_result.py
perigon/models/coordinate.py
perigon/models/coordinate_filter.py
perigon/models/entity_holder.py
perigon/models/error_response.py
perigon/models/event_type_holder.py
perigon/models/id_name_holder.py
perigon/models/illegal_parameter_exception.py
perigon/models/illegal_parameter_exception_cause.py
perigon/models/illegal_parameter_exception_cause_stack_trace_inner.py
perigon/models/illegal_parameter_exception_suppressed_inner.py
perigon/models/image_holder.py
perigon/models/internal_error_exception.py
perigon/models/journalist.py
perigon/models/journalist_search_result.py
perigon/models/key_point.py
perigon/models/keyword_holder.py
perigon/models/label_holder.py
perigon/models/location_count.py
perigon/models/location_holder.py
perigon/models/name_count.py
perigon/models/news_cluster.py
perigon/models/not_found_exception.py
perigon/models/people_search_result.py
perigon/models/person.py
perigon/models/person_count.py
perigon/models/person_holder.py
perigon/models/place.py
perigon/models/query_search_result.py
perigon/models/question.py
perigon/models/record_stat_holder.py
perigon/models/scored_article.py
perigon/models/scored_data_article.py
perigon/models/scored_data_wiki_data.py
perigon-1.5.0.dist-info/METADATA
perigon-1.5.0.dist-info/WHEEL
perigon-1.5.0.dist-info/licenses/LICENSE
perigon-1.5.0.dist-info/RECORD
