Metadata-Version: 2.4
Name: perigon
Version: 1.5.0
Summary: Perigon API
License: NoLicense
License-File: LICENSE
Keywords: OpenAPI,OpenAPI-Generator,Perigon API
Author: Perigon Support
Author-email: data@perigon.io
Requires-Python: >=3.9,<4.0
Classifier: License :: Other/Proprietary License
Classifier: Programming Language :: Python :: 3
Classifier: Programming Language :: Python :: 3.9
Classifier: Programming Language :: Python :: 3.10
Classifier: Programming Language :: Python :: 3.11
Classifier: Programming Language :: Python :: 3.12
Classifier: Programming Language :: Python :: 3.13
Classifier: Programming Language :: Python :: 3.14
Requires-Dist: httpx (>=0.27,<1.0)
Requires-Dist: pydantic (>=2)
Requires-Dist: python-dateutil (>=2.8.2)
Requires-Dist: typing-extensions (>=4.7.1)
Project-URL: Repository, https://github.com/goperigon/perigon-python
